dummy.py
setup.py
brokolit.egg-info/PKG-INFO
brokolit.egg-info/SOURCES.txt
brokolit.egg-info/dependency_links.txt
brokolit.egg-info/top_level.txt