Metadata-Version: 2.1
Name: brokolit
Version: 0.0.1
Summary: A harmless dummy test package
Author: Your Name
Author-email: you@example.com
